README.md
exall.py
setup.cfg
setup.py
exall.egg-info/PKG-INFO
exall.egg-info/SOURCES.txt
exall.egg-info/dependency_links.txt
exall.egg-info/top_level.txt