Metadata-Version: 1.0
Name: exall
Version: 0.11
Summary: Exall is an exception manager based on decorator/context/callback.  https://github.com/nongiach/exall/
Home-page: https://github.com/nongiach/exall/
Author: @chaign_c
Author-email: chaignc@hexpresso.fr
License: UNKNOWN
Keywords: exception,except,callback,raise,python
Platform: UNKNOWN
